{"nodes": [{"id": "d_the_app_src_services_notificationservice_js", "label": "notificationService.js", "file_type": "code", "source_file": "D:\\The App\\src\\services\\notificationService.js", "source_location": "L1"}, {"id": "services_notificationservice_study_tips", "label": "STUDY_TIPS", "file_type": "code", "source_file": "D:\\The App\\src\\services\\notificationService.js", "source_location": "L23"}, {"id": "services_notificationservice_gettodaynotificationkey", "label": "getTodayNotificationKey()", "file_type": "code", "source_file": "D:\\The App\\src\\services\\notificationService.js", "source_location": "L43"}, {"id": "services_notificationservice_wasstreakmilestonesenttoday", "label": "wasStreakMilestoneSentToday()", "file_type": "code", "source_file": "D:\\The App\\src\\services\\notificationService.js", "source_location": "L45"}, {"id": "services_notificationservice_markstreakmilestonesenttoday", "label": "markStreakMilestoneSentToday()", "file_type": "code", "source_file": "D:\\The App\\src\\services\\notificationService.js", "source_location": "L58"}, {"id": "services_notificationservice_ensurenotificationhandler", "label": "ensureNotificationHandler()", "file_type": "code", "source_file": "D:\\The App\\src\\services\\notificationService.js", "source_location": "L79"}, {"id": "services_notificationservice_requestpermissions", "label": "requestPermissions()", "file_type": "code", "source_file": "D:\\The App\\src\\services\\notificationService.js", "source_location": "L99"}, {"id": "services_notificationservice_scheduleallnotifications", "label": "scheduleAllNotifications()", "file_type": "code", "source_file": "D:\\The App\\src\\services\\notificationService.js", "source_location": "L113"}, {"id": "services_notificationservice_triggertodaynotifications", "label": "triggerTodayNotifications()", "file_type": "code", "source_file": "D:\\The App\\src\\services\\notificationService.js", "source_location": "L174"}, {"id": "services_notificationservice_triggerstreakmilestone", "label": "triggerStreakMilestone()", "file_type": "code", "source_file": "D:\\The App\\src\\services\\notificationService.js", "source_location": "L213"}, {"id": "services_notificationservice_sendwebinarnotification", "label": "sendWebinarNotification()", "file_type": "code", "source_file": "D:\\The App\\src\\services\\notificationService.js", "source_location": "L260"}, {"id": "services_notificationservice_webinarsubscriptionlisteners", "label": "webinarSubscriptionListeners", "file_type": "code", "source_file": "D:\\The App\\src\\services\\notificationService.js", "source_location": "L309"}, {"id": "services_notificationservice_emitwebinarsubscriptionchange", "label": "emitWebinarSubscriptionChange()", "file_type": "code", "source_file": "D:\\The App\\src\\services\\notificationService.js", "source_location": "L311"}, {"id": "services_notificationservice_addwebinarsubscriptionlistener", "label": "addWebinarSubscriptionListener()", "file_type": "code", "source_file": "D:\\The App\\src\\services\\notificationService.js", "source_location": "L321"}, {"id": "services_notificationservice_issubscribedtowebinarnotifications", "label": "isSubscribedToWebinarNotifications()", "file_type": "code", "source_file": "D:\\The App\\src\\services\\notificationService.js", "source_location": "L329"}, {"id": "services_notificationservice_unsubscribefromwebinarnotifications", "label": "unsubscribeFromWebinarNotifications()", "file_type": "code", "source_file": "D:\\The App\\src\\services\\notificationService.js", "source_location": "L346"}, {"id": "services_notificationservice_subscribetowebinarnotifications", "label": "subscribeToWebinarNotifications()", "file_type": "code", "source_file": "D:\\The App\\src\\services\\notificationService.js", "source_location": "L363"}, {"id": "services_notificationservice_setupnotificationtaphandler", "label": "setupNotificationTapHandler()", "file_type": "code", "source_file": "D:\\The App\\src\\services\\notificationService.js", "source_location": "L385"}, {"id": "services_notificationservice_sendvideonotification", "label": "sendVideoNotification()", "file_type": "code", "source_file": "D:\\The App\\src\\services\\notificationService.js", "source_location": "L403"}, {"id": "services_notificationservice_sendreplynotification", "label": "sendReplyNotification()", "file_type": "code", "source_file": "D:\\The App\\src\\services\\notificationService.js", "source_location": "L441"}, {"id": "services_notificationservice_videosubscriptionlisteners", "label": "videoSubscriptionListeners", "file_type": "code", "source_file": "D:\\The App\\src\\services\\notificationService.js", "source_location": "L488"}, {"id": "services_notificationservice_emitvideosubscriptionchange", "label": "emitVideoSubscriptionChange()", "file_type": "code", "source_file": "D:\\The App\\src\\services\\notificationService.js", "source_location": "L490"}, {"id": "services_notificationservice_persistvideonotificationpreference", "label": "persistVideoNotificationPreference()", "file_type": "code", "source_file": "D:\\The App\\src\\services\\notificationService.js", "source_location": "L500"}, {"id": "services_notificationservice_addvideosubscriptionlistener", "label": "addVideoSubscriptionListener()", "file_type": "code", "source_file": "D:\\The App\\src\\services\\notificationService.js", "source_location": "L520"}, {"id": "services_notificationservice_issubscribedtovideonotifications", "label": "isSubscribedToVideoNotifications()", "file_type": "code", "source_file": "D:\\The App\\src\\services\\notificationService.js", "source_location": "L525"}, {"id": "services_notificationservice_unsubscribefromvideonotifications", "label": "unsubscribeFromVideoNotifications()", "file_type": "code", "source_file": "D:\\The App\\src\\services\\notificationService.js", "source_location": "L548"}, {"id": "services_notificationservice_subscribetovideonotifications", "label": "subscribeToVideoNotifications()", "file_type": "code", "source_file": "D:\\The App\\src\\services\\notificationService.js", "source_location": "L560"}], "edges": [{"source": "d_the_app_src_services_notificationservice_js", "target": "expo_notifications", "relation": "imports_from", "context": "import", "confidence": "EXTRACTED", "source_file": "D:\\The App\\src\\services\\notificationService.js", "source_location": "L14", "weight": 1.0}, {"source": "d_the_app_src_services_notificationservice_js", "target": "expo_device", "relation": "imports_from", "context": "import", "confidence": "EXTRACTED", "source_file": "D:\\The App\\src\\services\\notificationService.js", "source_location": "L15", "weight": 1.0}, {"source": "d_the_app_src_services_notificationservice_js", "target": "async_storage", "relation": "imports_from", "context": "import", "confidence": "EXTRACTED", "source_file": "D:\\The App\\src\\services\\notificationService.js", "source_location": "L16", "weight": 1.0}, {"source": "d_the_app_src_services_notificationservice_js", "target": "react_native", "relation": "imports_from", "context": "import", "confidence": "EXTRACTED", "source_file": "D:\\The App\\src\\services\\notificationService.js", "source_location": "L17", "weight": 1.0}, {"source": "d_the_app_src_services_notificationservice_js", "target": "firestore", "relation": "imports_from", "context": "import", "confidence": "EXTRACTED", "source_file": "D:\\The App\\src\\services\\notificationService.js", "source_location": "L18", "weight": 1.0}, {"source": "d_the_app_src_services_notificationservice_js", "target": "d_the_app_src_config_firebase_js", "relation": "imports_from", "context": "import", "confidence": "EXTRACTED", "source_file": "D:\\The App\\src\\services\\notificationService.js", "source_location": "L19", "weight": 1.0}, {"source": "d_the_app_src_services_notificationservice_js", "target": "config_firebase_auth", "relation": "imports", "context": "import", "confidence": "EXTRACTED", "source_file": "D:\\The App\\src\\services\\notificationService.js", "source_location": "L19", "weight": 1.0}, {"source": "d_the_app_src_services_notificationservice_js", "target": "config_firebase_db", "relation": "imports", "context": "import", "confidence": "EXTRACTED", "source_file": "D:\\The App\\src\\services\\notificationService.js", "source_location": "L19", "weight": 1.0}, {"source": "d_the_app_src_services_notificationservice_js", "target": "d_the_app_src_data_publichealthdays_json", "relation": "imports_from", "context": "import", "confidence": "EXTRACTED", "source_file": "D:\\The App\\src\\services\\notificationService.js", "source_location": "L20", "weight": 1.0}, {"source": "d_the_app_src_services_notificationservice_js", "target": "services_notificationservice_study_tips", "relation": "contains", "confidence": "EXTRACTED", "source_file": "D:\\The App\\src\\services\\notificationService.js", "source_location": "L23", "weight": 1.0}, {"source": "d_the_app_src_services_notificationservice_js", "target": "services_notificationservice_gettodaynotificationkey", "relation": "contains", "confidence": "EXTRACTED", "source_file": "D:\\The App\\src\\services\\notificationService.js", "source_location": "L43", "weight": 1.0}, {"source": "d_the_app_src_services_notificationservice_js", "target": "services_notificationservice_wasstreakmilestonesenttoday", "relation": "contains", "confidence": "EXTRACTED", "source_file": "D:\\The App\\src\\services\\notificationService.js", "source_location": "L45", "weight": 1.0}, {"source": "d_the_app_src_services_notificationservice_js", "target": "services_notificationservice_markstreakmilestonesenttoday", "relation": "contains", "confidence": "EXTRACTED", "source_file": "D:\\The App\\src\\services\\notificationService.js", "source_location": "L58", "weight": 1.0}, {"source": "d_the_app_src_services_notificationservice_js", "target": "services_notificationservice_ensurenotificationhandler", "relation": "contains", "confidence": "EXTRACTED", "source_file": "D:\\The App\\src\\services\\notificationService.js", "source_location": "L79", "weight": 1.0}, {"source": "d_the_app_src_services_notificationservice_js", "target": "services_notificationservice_requestpermissions", "relation": "contains", "confidence": "EXTRACTED", "source_file": "D:\\The App\\src\\services\\notificationService.js", "source_location": "L99", "weight": 1.0}, {"source": "d_the_app_src_services_notificationservice_js", "target": "services_notificationservice_scheduleallnotifications", "relation": "contains", "confidence": "EXTRACTED", "source_file": "D:\\The App\\src\\services\\notificationService.js", "source_location": "L113", "weight": 1.0}, {"source": "d_the_app_src_services_notificationservice_js", "target": "services_notificationservice_triggertodaynotifications", "relation": "contains", "confidence": "EXTRACTED", "source_file": "D:\\The App\\src\\services\\notificationService.js", "source_location": "L174", "weight": 1.0}, {"source": "d_the_app_src_services_notificationservice_js", "target": "services_notificationservice_triggerstreakmilestone", "relation": "contains", "confidence": "EXTRACTED", "source_file": "D:\\The App\\src\\services\\notificationService.js", "source_location": "L213", "weight": 1.0}, {"source": "d_the_app_src_services_notificationservice_js", "target": "services_notificationservice_sendwebinarnotification", "relation": "contains", "confidence": "EXTRACTED", "source_file": "D:\\The App\\src\\services\\notificationService.js", "source_location": "L260", "weight": 1.0}, {"source": "d_the_app_src_services_notificationservice_js", "target": "services_notificationservice_webinarsubscriptionlisteners", "relation": "contains", "confidence": "EXTRACTED", "source_file": "D:\\The App\\src\\services\\notificationService.js", "source_location": "L309", "weight": 1.0}, {"source": "d_the_app_src_services_notificationservice_js", "target": "services_notificationservice_emitwebinarsubscriptionchange", "relation": "contains", "confidence": "EXTRACTED", "source_file": "D:\\The App\\src\\services\\notificationService.js", "source_location": "L311", "weight": 1.0}, {"source": "d_the_app_src_services_notificationservice_js", "target": "services_notificationservice_addwebinarsubscriptionlistener", "relation": "contains", "confidence": "EXTRACTED", "source_file": "D:\\The App\\src\\services\\notificationService.js", "source_location": "L321", "weight": 1.0}, {"source": "d_the_app_src_services_notificationservice_js", "target": "services_notificationservice_issubscribedtowebinarnotifications", "relation": "contains", "confidence": "EXTRACTED", "source_file": "D:\\The App\\src\\services\\notificationService.js", "source_location": "L329", "weight": 1.0}, {"source": "d_the_app_src_services_notificationservice_js", "target": "services_notificationservice_unsubscribefromwebinarnotifications", "relation": "contains", "confidence": "EXTRACTED", "source_file": "D:\\The App\\src\\services\\notificationService.js", "source_location": "L346", "weight": 1.0}, {"source": "d_the_app_src_services_notificationservice_js", "target": "services_notificationservice_subscribetowebinarnotifications", "relation": "contains", "confidence": "EXTRACTED", "source_file": "D:\\The App\\src\\services\\notificationService.js", "source_location": "L363", "weight": 1.0}, {"source": "d_the_app_src_services_notificationservice_js", "target": "services_notificationservice_setupnotificationtaphandler", "relation": "contains", "confidence": "EXTRACTED", "source_file": "D:\\The App\\src\\services\\notificationService.js", "source_location": "L385", "weight": 1.0}, {"source": "d_the_app_src_services_notificationservice_js", "target": "services_notificationservice_sendvideonotification", "relation": "contains", "confidence": "EXTRACTED", "source_file": "D:\\The App\\src\\services\\notificationService.js", "source_location": "L403", "weight": 1.0}, {"source": "d_the_app_src_services_notificationservice_js", "target": "services_notificationservice_sendreplynotification", "relation": "contains", "confidence": "EXTRACTED", "source_file": "D:\\The App\\src\\services\\notificationService.js", "source_location": "L441", "weight": 1.0}, {"source": "d_the_app_src_services_notificationservice_js", "target": "services_notificationservice_videosubscriptionlisteners", "relation": "contains", "confidence": "EXTRACTED", "source_file": "D:\\The App\\src\\services\\notificationService.js", "source_location": "L488", "weight": 1.0}, {"source": "d_the_app_src_services_notificationservice_js", "target": "services_notificationservice_emitvideosubscriptionchange", "relation": "contains", "confidence": "EXTRACTED", "source_file": "D:\\The App\\src\\services\\notificationService.js", "source_location": "L490", "weight": 1.0}, {"source": "d_the_app_src_services_notificationservice_js", "target": "services_notificationservice_persistvideonotificationpreference", "relation": "contains", "confidence": "EXTRACTED", "source_file": "D:\\The App\\src\\services\\notificationService.js", "source_location": "L500", "weight": 1.0}, {"source": "d_the_app_src_services_notificationservice_js", "target": "services_notificationservice_addvideosubscriptionlistener", "relation": "contains", "confidence": "EXTRACTED", "source_file": "D:\\The App\\src\\services\\notificationService.js", "source_location": "L520", "weight": 1.0}, {"source": "d_the_app_src_services_notificationservice_js", "target": "services_notificationservice_issubscribedtovideonotifications", "relation": "contains", "confidence": "EXTRACTED", "source_file": "D:\\The App\\src\\services\\notificationService.js", "source_location": "L525", "weight": 1.0}, {"source": "d_the_app_src_services_notificationservice_js", "target": "services_notificationservice_unsubscribefromvideonotifications", "relation": "contains", "confidence": "EXTRACTED", "source_file": "D:\\The App\\src\\services\\notificationService.js", "source_location": "L548", "weight": 1.0}, {"source": "d_the_app_src_services_notificationservice_js", "target": "services_notificationservice_subscribetovideonotifications", "relation": "contains", "confidence": "EXTRACTED", "source_file": "D:\\The App\\src\\services\\notificationService.js", "source_location": "L560", "weight": 1.0}, {"source": "services_notificationservice_wasstreakmilestonesenttoday", "target": "services_notificationservice_gettodaynotificationkey", "relation": "calls", "context": "call", "confidence": "EXTRACTED", "source_file": "D:\\The App\\src\\services\\notificationService.js", "source_location": "L51", "weight": 1.0}, {"source": "services_notificationservice_markstreakmilestonesenttoday", "target": "services_notificationservice_gettodaynotificationkey", "relation": "calls", "context": "call", "confidence": "EXTRACTED", "source_file": "D:\\The App\\src\\services\\notificationService.js", "source_location": "L64", "weight": 1.0}, {"source": "services_notificationservice_scheduleallnotifications", "target": "services_notificationservice_ensurenotificationhandler", "relation": "calls", "context": "call", "confidence": "EXTRACTED", "source_file": "D:\\The App\\src\\services\\notificationService.js", "source_location": "L114", "weight": 1.0}, {"source": "services_notificationservice_scheduleallnotifications", "target": "services_notificationservice_requestpermissions", "relation": "calls", "context": "call", "confidence": "EXTRACTED", "source_file": "D:\\The App\\src\\services\\notificationService.js", "source_location": "L115", "weight": 1.0}, {"source": "services_notificationservice_scheduleallnotifications", "target": "services_notificationservice_triggertodaynotifications", "relation": "calls", "context": "call", "confidence": "EXTRACTED", "source_file": "D:\\The App\\src\\services\\notificationService.js", "source_location": "L167", "weight": 1.0}, {"source": "services_notificationservice_triggertodaynotifications", "target": "services_notificationservice_gettodaynotificationkey", "relation": "calls", "context": "call", "confidence": "EXTRACTED", "source_file": "D:\\The App\\src\\services\\notificationService.js", "source_location": "L179", "weight": 1.0}, {"source": "services_notificationservice_triggerstreakmilestone", "target": "services_notificationservice_wasstreakmilestonesenttoday", "relation": "calls", "context": "call", "confidence": "EXTRACTED", "source_file": "D:\\The App\\src\\services\\notificationService.js", "source_location": "L233", "weight": 1.0}, {"source": "services_notificationservice_triggerstreakmilestone", "target": "services_notificationservice_requestpermissions", "relation": "calls", "context": "call", "confidence": "EXTRACTED", "source_file": "D:\\The App\\src\\services\\notificationService.js", "source_location": "L235", "weight": 1.0}, {"source": "services_notificationservice_triggerstreakmilestone", "target": "services_notificationservice_markstreakmilestonesenttoday", "relation": "calls", "context": "call", "confidence": "EXTRACTED", "source_file": "D:\\The App\\src\\services\\notificationService.js", "source_location": "L250", "weight": 1.0}, {"source": "services_notificationservice_sendwebinarnotification", "target": "async_storage", "relation": "imports_from", "confidence": "EXTRACTED", "source_file": "D:\\The App\\src\\services\\notificationService.js", "source_location": "L269", "weight": 1.0}, {"source": "services_notificationservice_sendwebinarnotification", "target": "services_notificationservice_requestpermissions", "relation": "calls", "context": "call", "confidence": "EXTRACTED", "source_file": "D:\\The App\\src\\services\\notificationService.js", "source_location": "L280", "weight": 1.0}, {"source": "services_notificationservice_issubscribedtowebinarnotifications", "target": "async_storage", "relation": "imports_from", "confidence": "EXTRACTED", "source_file": "D:\\The App\\src\\services\\notificationService.js", "source_location": "L332", "weight": 1.0}, {"source": "services_notificationservice_unsubscribefromwebinarnotifications", "target": "async_storage", "relation": "imports_from", "confidence": "EXTRACTED", "source_file": "D:\\The App\\src\\services\\notificationService.js", "source_location": "L349", "weight": 1.0}, {"source": "services_notificationservice_unsubscribefromwebinarnotifications", "target": "services_notificationservice_emitwebinarsubscriptionchange", "relation": "calls", "context": "call", "confidence": "EXTRACTED", "source_file": "D:\\The App\\src\\services\\notificationService.js", "source_location": "L352", "weight": 1.0}, {"source": "services_notificationservice_subscribetowebinarnotifications", "target": "async_storage", "relation": "imports_from", "confidence": "EXTRACTED", "source_file": "D:\\The App\\src\\services\\notificationService.js", "source_location": "L366", "weight": 1.0}, {"source": "services_notificationservice_subscribetowebinarnotifications", "target": "services_notificationservice_emitwebinarsubscriptionchange", "relation": "calls", "context": "call", "confidence": "EXTRACTED", "source_file": "D:\\The App\\src\\services\\notificationService.js", "source_location": "L372", "weight": 1.0}, {"source": "services_notificationservice_sendvideonotification", "target": "services_notificationservice_issubscribedtovideonotifications", "relation": "calls", "context": "call", "confidence": "EXTRACTED", "source_file": "D:\\The App\\src\\services\\notificationService.js", "source_location": "L405", "weight": 1.0}, {"source": "services_notificationservice_sendvideonotification", "target": "services_notificationservice_requestpermissions", "relation": "calls", "context": "call", "confidence": "EXTRACTED", "source_file": "D:\\The App\\src\\services\\notificationService.js", "source_location": "L412", "weight": 1.0}, {"source": "services_notificationservice_issubscribedtovideonotifications", "target": "services_notificationservice_persistvideonotificationpreference", "relation": "calls", "context": "call", "confidence": "EXTRACTED", "source_file": "D:\\The App\\src\\services\\notificationService.js", "source_location": "L537", "weight": 1.0}, {"source": "services_notificationservice_unsubscribefromvideonotifications", "target": "services_notificationservice_persistvideonotificationpreference", "relation": "calls", "context": "call", "confidence": "EXTRACTED", "source_file": "D:\\The App\\src\\services\\notificationService.js", "source_location": "L550", "weight": 1.0}, {"source": "services_notificationservice_unsubscribefromvideonotifications", "target": "services_notificationservice_emitvideosubscriptionchange", "relation": "calls", "context": "call", "confidence": "EXTRACTED", "source_file": "D:\\The App\\src\\services\\notificationService.js", "source_location": "L552", "weight": 1.0}, {"source": "services_notificationservice_subscribetovideonotifications", "target": "services_notificationservice_persistvideonotificationpreference", "relation": "calls", "context": "call", "confidence": "EXTRACTED", "source_file": "D:\\The App\\src\\services\\notificationService.js", "source_location": "L562", "weight": 1.0}, {"source": "services_notificationservice_subscribetovideonotifications", "target": "services_notificationservice_emitvideosubscriptionchange", "relation": "calls", "context": "call", "confidence": "EXTRACTED", "source_file": "D:\\The App\\src\\services\\notificationService.js", "source_location": "L564", "weight": 1.0}], "raw_calls": [{"caller_nid": "services_notificationservice_gettodaynotificationkey", "callee": "split", "is_member_call": true, "source_file": "D:\\The App\\src\\services\\notificationService.js", "source_location": "L43"}, {"caller_nid": "services_notificationservice_gettodaynotificationkey", "callee": "toISOString", "is_member_call": true, "source_file": "D:\\The App\\src\\services\\notificationService.js", "source_location": "L43"}, {"caller_nid": "services_notificationservice_wasstreakmilestonesenttoday", "callee": "getItem", "is_member_call": true, "source_file": "D:\\The App\\src\\services\\notificationService.js", "source_location": "L47"}, {"caller_nid": "services_notificationservice_wasstreakmilestonesenttoday", "callee": "parse", "is_member_call": true, "source_file": "D:\\The App\\src\\services\\notificationService.js", "source_location": "L50"}, {"caller_nid": "services_notificationservice_wasstreakmilestonesenttoday", "callee": "warn", "is_member_call": true, "source_file": "D:\\The App\\src\\services\\notificationService.js", "source_location": "L53"}, {"caller_nid": "services_notificationservice_markstreakmilestonesenttoday", "callee": "getItem", "is_member_call": true, "source_file": "D:\\The App\\src\\services\\notificationService.js", "source_location": "L60"}, {"caller_nid": "services_notificationservice_markstreakmilestonesenttoday", "callee": "parse", "is_member_call": true, "source_file": "D:\\The App\\src\\services\\notificationService.js", "source_location": "L63"}, {"caller_nid": "services_notificationservice_markstreakmilestonesenttoday", "callee": "setItem", "is_member_call": true, "source_file": "D:\\The App\\src\\services\\notificationService.js", "source_location": "L65"}, {"caller_nid": "services_notificationservice_markstreakmilestonesenttoday", "callee": "stringify", "is_member_call": true, "source_file": "D:\\The App\\src\\services\\notificationService.js", "source_location": "L67"}, {"caller_nid": "services_notificationservice_markstreakmilestonesenttoday", "callee": "warn", "is_member_call": true, "source_file": "D:\\The App\\src\\services\\notificationService.js", "source_location": "L70"}, {"caller_nid": "services_notificationservice_ensurenotificationhandler", "callee": "setNotificationHandler", "is_member_call": true, "source_file": "D:\\The App\\src\\services\\notificationService.js", "source_location": "L83"}, {"caller_nid": "services_notificationservice_requestpermissions", "callee": "getPermissionsAsync", "is_member_call": true, "source_file": "D:\\The App\\src\\services\\notificationService.js", "source_location": "L102"}, {"caller_nid": "services_notificationservice_requestpermissions", "callee": "requestPermissionsAsync", "is_member_call": true, "source_file": "D:\\The App\\src\\services\\notificationService.js", "source_location": "L105"}, {"caller_nid": "services_notificationservice_scheduleallnotifications", "callee": "cancelAllScheduledNotificationsAsync", "is_member_call": true, "source_file": "D:\\The App\\src\\services\\notificationService.js", "source_location": "L119"}, {"caller_nid": "services_notificationservice_scheduleallnotifications", "callee": "scheduleNotificationAsync", "is_member_call": true, "source_file": "D:\\The App\\src\\services\\notificationService.js", "source_location": "L122"}, {"caller_nid": "services_notificationservice_scheduleallnotifications", "callee": "includes", "is_member_call": true, "source_file": "D:\\The App\\src\\services\\notificationService.js", "source_location": "L142"}, {"caller_nid": "services_notificationservice_scheduleallnotifications", "callee": "scheduleNotificationAsync", "is_member_call": true, "source_file": "D:\\The App\\src\\services\\notificationService.js", "source_location": "L146"}, {"caller_nid": "services_notificationservice_scheduleallnotifications", "callee": "split", "is_member_call": true, "source_file": "D:\\The App\\src\\services\\notificationService.js", "source_location": "L150"}, {"caller_nid": "services_notificationservice_triggertodaynotifications", "callee": "getMonth", "is_member_call": true, "source_file": "D:\\The App\\src\\services\\notificationService.js", "source_location": "L176"}, {"caller_nid": "services_notificationservice_triggertodaynotifications", "callee": "getDate", "is_member_call": true, "source_file": "D:\\The App\\src\\services\\notificationService.js", "source_location": "L177"}, {"caller_nid": "services_notificationservice_triggertodaynotifications", "callee": "getItem", "is_member_call": true, "source_file": "D:\\The App\\src\\services\\notificationService.js", "source_location": "L183"}, {"caller_nid": "services_notificationservice_triggertodaynotifications", "callee": "find", "is_member_call": true, "source_file": "D:\\The App\\src\\services\\notificationService.js", "source_location": "L187"}, {"caller_nid": "services_notificationservice_triggertodaynotifications", "callee": "includes", "is_member_call": true, "source_file": "D:\\The App\\src\\services\\notificationService.js", "source_location": "L189"}, {"caller_nid": "services_notificationservice_triggertodaynotifications", "callee": "scheduleNotificationAsync", "is_member_call": true, "source_file": "D:\\The App\\src\\services\\notificationService.js", "source_location": "L193"}, {"caller_nid": "services_notificationservice_triggertodaynotifications", "callee": "split", "is_member_call": true, "source_file": "D:\\The App\\src\\services\\notificationService.js", "source_location": "L196"}, {"caller_nid": "services_notificationservice_triggertodaynotifications", "callee": "setItem", "is_member_call": true, "source_file": "D:\\The App\\src\\services\\notificationService.js", "source_location": "L202"}, {"caller_nid": "services_notificationservice_triggertodaynotifications", "callee": "warn", "is_member_call": true, "source_file": "D:\\The App\\src\\services\\notificationService.js", "source_location": "L205"}, {"caller_nid": "services_notificationservice_triggerstreakmilestone", "callee": "scheduleNotificationAsync", "is_member_call": true, "source_file": "D:\\The App\\src\\services\\notificationService.js", "source_location": "L240"}, {"caller_nid": "services_notificationservice_sendwebinarnotification", "callee": "getItem", "is_member_call": true, "source_file": "D:\\The App\\src\\services\\notificationService.js", "source_location": "L270"}, {"caller_nid": "services_notificationservice_sendwebinarnotification", "callee": "log", "is_member_call": true, "source_file": "D:\\The App\\src\\services\\notificationService.js", "source_location": "L275"}, {"caller_nid": "services_notificationservice_sendwebinarnotification", "callee": "log", "is_member_call": true, "source_file": "D:\\The App\\src\\services\\notificationService.js", "source_location": "L282"}, {"caller_nid": "services_notificationservice_sendwebinarnotification", "callee": "scheduleNotificationAsync", "is_member_call": true, "source_file": "D:\\The App\\src\\services\\notificationService.js", "source_location": "L287"}, {"caller_nid": "services_notificationservice_sendwebinarnotification", "callee": "log", "is_member_call": true, "source_file": "D:\\The App\\src\\services\\notificationService.js", "source_location": "L302"}, {"caller_nid": "services_notificationservice_sendwebinarnotification", "callee": "error", "is_member_call": true, "source_file": "D:\\The App\\src\\services\\notificationService.js", "source_location": "L304"}, {"caller_nid": "services_notificationservice_emitwebinarsubscriptionchange", "callee": "forEach", "is_member_call": true, "source_file": "D:\\The App\\src\\services\\notificationService.js", "source_location": "L312"}, {"caller_nid": "services_notificationservice_addwebinarsubscriptionlistener", "callee": "add", "is_member_call": true, "source_file": "D:\\The App\\src\\services\\notificationService.js", "source_location": "L322"}, {"caller_nid": "services_notificationservice_issubscribedtowebinarnotifications", "callee": "getItem", "is_member_call": true, "source_file": "D:\\The App\\src\\services\\notificationService.js", "source_location": "L333"}, {"caller_nid": "services_notificationservice_issubscribedtowebinarnotifications", "callee": "error", "is_member_call": true, "source_file": "D:\\The App\\src\\services\\notificationService.js", "source_location": "L338"}, {"caller_nid": "services_notificationservice_unsubscribefromwebinarnotifications", "callee": "removeItem", "is_member_call": true, "source_file": "D:\\The App\\src\\services\\notificationService.js", "source_location": "L350"}, {"caller_nid": "services_notificationservice_unsubscribefromwebinarnotifications", "callee": "log", "is_member_call": true, "source_file": "D:\\The App\\src\\services\\notificationService.js", "source_location": "L351"}, {"caller_nid": "services_notificationservice_unsubscribefromwebinarnotifications", "callee": "error", "is_member_call": true, "source_file": "D:\\The App\\src\\services\\notificationService.js", "source_location": "L355"}, {"caller_nid": "services_notificationservice_subscribetowebinarnotifications", "callee": "setItem", "is_member_call": true, "source_file": "D:\\The App\\src\\services\\notificationService.js", "source_location": "L367"}, {"caller_nid": "services_notificationservice_subscribetowebinarnotifications", "callee": "log", "is_member_call": true, "source_file": "D:\\The App\\src\\services\\notificationService.js", "source_location": "L371"}, {"caller_nid": "services_notificationservice_subscribetowebinarnotifications", "callee": "error", "is_member_call": true, "source_file": "D:\\The App\\src\\services\\notificationService.js", "source_location": "L375"}, {"caller_nid": "services_notificationservice_setupnotificationtaphandler", "callee": "addNotificationResponseReceivedListener", "is_member_call": true, "source_file": "D:\\The App\\src\\services\\notificationService.js", "source_location": "L386"}, {"caller_nid": "services_notificationservice_sendvideonotification", "callee": "log", "is_member_call": true, "source_file": "D:\\The App\\src\\services\\notificationService.js", "source_location": "L408"}, {"caller_nid": "services_notificationservice_sendvideonotification", "callee": "log", "is_member_call": true, "source_file": "D:\\The App\\src\\services\\notificationService.js", "source_location": "L414"}, {"caller_nid": "services_notificationservice_sendvideonotification", "callee": "scheduleNotificationAsync", "is_member_call": true, "source_file": "D:\\The App\\src\\services\\notificationService.js", "source_location": "L418"}, {"caller_nid": "services_notificationservice_sendvideonotification", "callee": "log", "is_member_call": true, "source_file": "D:\\The App\\src\\services\\notificationService.js", "source_location": "L435"}, {"caller_nid": "services_notificationservice_sendvideonotification", "callee": "error", "is_member_call": true, "source_file": "D:\\The App\\src\\services\\notificationService.js", "source_location": "L437"}, {"caller_nid": "services_notificationservice_sendreplynotification", "callee": "startsWith", "is_member_call": true, "source_file": "D:\\The App\\src\\services\\notificationService.js", "source_location": "L444"}, {"caller_nid": "services_notificationservice_sendreplynotification", "callee": "startsWith", "is_member_call": true, "source_file": "D:\\The App\\src\\services\\notificationService.js", "source_location": "L445"}, {"caller_nid": "services_notificationservice_sendreplynotification", "callee": "fetch", "is_member_call": false, "source_file": "D:\\The App\\src\\services\\notificationService.js", "source_location": "L454"}, {"caller_nid": "services_notificationservice_sendreplynotification", "callee": "stringify", "is_member_call": true, "source_file": "D:\\The App\\src\\services\\notificationService.js", "source_location": "L461"}, {"caller_nid": "services_notificationservice_sendreplynotification", "callee": "text", "is_member_call": true, "source_file": "D:\\The App\\src\\services\\notificationService.js", "source_location": "L476"}, {"caller_nid": "services_notificationservice_sendreplynotification", "callee": "warn", "is_member_call": true, "source_file": "D:\\The App\\src\\services\\notificationService.js", "source_location": "L477"}, {"caller_nid": "services_notificationservice_sendreplynotification", "callee": "warn", "is_member_call": true, "source_file": "D:\\The App\\src\\services\\notificationService.js", "source_location": "L483"}, {"caller_nid": "services_notificationservice_emitvideosubscriptionchange", "callee": "forEach", "is_member_call": true, "source_file": "D:\\The App\\src\\services\\notificationService.js", "source_location": "L491"}, {"caller_nid": "services_notificationservice_persistvideonotificationpreference", "callee": "setItem", "is_member_call": true, "source_file": "D:\\The App\\src\\services\\notificationService.js", "source_location": "L501"}, {"caller_nid": "services_notificationservice_persistvideonotificationpreference", "callee": "removeItem", "is_member_call": true, "source_file": "D:\\The App\\src\\services\\notificationService.js", "source_location": "L505"}, {"caller_nid": "services_notificationservice_persistvideonotificationpreference", "callee": "setDoc", "is_member_call": false, "source_file": "D:\\The App\\src\\services\\notificationService.js", "source_location": "L510"}, {"caller_nid": "services_notificationservice_persistvideonotificationpreference", "callee": "doc", "is_member_call": false, "source_file": "D:\\The App\\src\\services\\notificationService.js", "source_location": "L511"}, {"caller_nid": "services_notificationservice_persistvideonotificationpreference", "callee": "serverTimestamp", "is_member_call": false, "source_file": "D:\\The App\\src\\services\\notificationService.js", "source_location": "L514"}, {"caller_nid": "services_notificationservice_addvideosubscriptionlistener", "callee": "add", "is_member_call": true, "source_file": "D:\\The App\\src\\services\\notificationService.js", "source_location": "L521"}, {"caller_nid": "services_notificationservice_issubscribedtovideonotifications", "callee": "getItem", "is_member_call": true, "source_file": "D:\\The App\\src\\services\\notificationService.js", "source_location": "L527"}, {"caller_nid": "services_notificationservice_issubscribedtovideonotifications", "callee": "getItem", "is_member_call": true, "source_file": "D:\\The App\\src\\services\\notificationService.js", "source_location": "L532"}, {"caller_nid": "services_notificationservice_issubscribedtovideonotifications", "callee": "error", "is_member_call": true, "source_file": "D:\\The App\\src\\services\\notificationService.js", "source_location": "L543"}, {"caller_nid": "services_notificationservice_unsubscribefromvideonotifications", "callee": "log", "is_member_call": true, "source_file": "D:\\The App\\src\\services\\notificationService.js", "source_location": "L551"}, {"caller_nid": "services_notificationservice_unsubscribefromvideonotifications", "callee": "error", "is_member_call": true, "source_file": "D:\\The App\\src\\services\\notificationService.js", "source_location": "L555"}, {"caller_nid": "services_notificationservice_subscribetovideonotifications", "callee": "log", "is_member_call": true, "source_file": "D:\\The App\\src\\services\\notificationService.js", "source_location": "L563"}, {"caller_nid": "services_notificationservice_subscribetovideonotifications", "callee": "error", "is_member_call": true, "source_file": "D:\\The App\\src\\services\\notificationService.js", "source_location": "L567"}]}