{"nodes": [{"id": "scripts_dump_review_doc_js", "label": "dump_review_doc.js", "file_type": "code", "source_file": "scripts\\dump_review_doc.js", "source_location": "L1"}, {"id": "dump_review_doc_main", "label": "main()", "file_type": "code", "source_file": "scripts\\dump_review_doc.js", "source_location": "L13"}], "edges": [{"source": "scripts_dump_review_doc_js", "target": "dump_review_doc_main", "relation": "contains", "confidence": "EXTRACTED", "source_file": "scripts\\dump_review_doc.js", "source_location": "L13", "weight": 1.0}], "raw_calls": [{"caller_nid": "dump_review_doc_main", "callee": "get", "source_file": "scripts\\dump_review_doc.js", "source_location": "L14"}, {"caller_nid": "dump_review_doc_main", "callee": "limit", "source_file": "scripts\\dump_review_doc.js", "source_location": "L14"}, {"caller_nid": "dump_review_doc_main", "callee": "collection", "source_file": "scripts\\dump_review_doc.js", "source_location": "L14"}, {"caller_nid": "dump_review_doc_main", "callee": "firestore", "source_file": "scripts\\dump_review_doc.js", "source_location": "L14"}, {"caller_nid": "dump_review_doc_main", "callee": "log", "source_file": "scripts\\dump_review_doc.js", "source_location": "L20"}, {"caller_nid": "dump_review_doc_main", "callee": "log", "source_file": "scripts\\dump_review_doc.js", "source_location": "L23"}, {"caller_nid": "dump_review_doc_main", "callee": "log", "source_file": "scripts\\dump_review_doc.js", "source_location": "L24"}, {"caller_nid": "dump_review_doc_main", "callee": "stringify", "source_file": "scripts\\dump_review_doc.js", "source_location": "L24"}, {"caller_nid": "dump_review_doc_main", "callee": "keys", "source_file": "scripts\\dump_review_doc.js", "source_location": "L24"}, {"caller_nid": "dump_review_doc_main", "callee": "data", "source_file": "scripts\\dump_review_doc.js", "source_location": "L24"}, {"caller_nid": "dump_review_doc_main", "callee": "data", "source_file": "scripts\\dump_review_doc.js", "source_location": "L25"}, {"caller_nid": "dump_review_doc_main", "callee": "log", "source_file": "scripts\\dump_review_doc.js", "source_location": "L27"}, {"caller_nid": "dump_review_doc_main", "callee": "log", "source_file": "scripts\\dump_review_doc.js", "source_location": "L28"}, {"caller_nid": "dump_review_doc_main", "callee": "log", "source_file": "scripts\\dump_review_doc.js", "source_location": "L29"}, {"caller_nid": "dump_review_doc_main", "callee": "log", "source_file": "scripts\\dump_review_doc.js", "source_location": "L30"}, {"caller_nid": "dump_review_doc_main", "callee": "log", "source_file": "scripts\\dump_review_doc.js", "source_location": "L31"}, {"caller_nid": "dump_review_doc_main", "callee": "log", "source_file": "scripts\\dump_review_doc.js", "source_location": "L32"}, {"caller_nid": "dump_review_doc_main", "callee": "isArray", "source_file": "scripts\\dump_review_doc.js", "source_location": "L32"}, {"caller_nid": "dump_review_doc_main", "callee": "isArray", "source_file": "scripts\\dump_review_doc.js", "source_location": "L32"}, {"caller_nid": "dump_review_doc_main", "callee": "exit", "source_file": "scripts\\dump_review_doc.js", "source_location": "L35"}]}